flask_kale.py
setup.py
Flask_kale.egg-info/PKG-INFO
Flask_kale.egg-info/SOURCES.txt
Flask_kale.egg-info/dependency_links.txt
Flask_kale.egg-info/requires.txt
Flask_kale.egg-info/top_level.txt