Metadata-Version: 1.0
Name: Flask-kale
Version: 0.1
Summary: Use kale models on a flask project
Home-page: https://github.com/uniphil/flask-kale
Author: Phil Schleihauf
Author-email: uniphil@gmail.com
License: dwtfyw with optional coffee stipulation (one large dark black)
Platform: UNKNOWN
